ltspice/__init__.py
ltspice/ltspice.py
ltspice-1.0.5.dist-info/LICENSE.txt
ltspice-1.0.5.dist-info/METADATA
ltspice-1.0.5.dist-info/WHEEL
ltspice-1.0.5.dist-info/top_level.txt
ltspice-1.0.5.dist-info/RECORD
