Metadata-Version: 2.1
Name: ltspice
Version: 1.0.5
Summary: DESC
Home-page: https://github.com/DongHoonPark/ltspice_pytool
Author: DonghoonPark
Author-email: donghun94@snu.ac.kr
License: MIT
Download-URL: https://pypi.org/project/ltspice
Keywords: ltspice,circuit data analysis,multi point simulation
Platform: UNKNOWN
Classifier: License :: OSI Approved :: MIT License
Classifier: Programming Language :: Python :: 3
Classifier: Programming Language :: Python :: 3.7
Classifier: Programming Language :: Python :: 3.8
Classifier: Programming Language :: Python :: 3.9
License-File: LICENSE.txt
Requires-Dist: numpy
Requires-Dist: deprecated
Requires-Dist: matplotlib
